daily_active_users/__init__.py
daily_active_users/admin.py
daily_active_users/apps.py
daily_active_users/middleware.py
daily_active_users/models.py
daily_active_users/migrations/0001_initial.py
daily_active_users/migrations/__init__.py
daily_active_users-0.1.2.dist-info/LICENSE
daily_active_users-0.1.2.dist-info/METADATA
daily_active_users-0.1.2.dist-info/WHEEL
daily_active_users-0.1.2.dist-info/top_level.txt
daily_active_users-0.1.2.dist-info/RECORD
