Metadata-Version: 2.1
Name: daily-active-users
Version: 0.1.2
Summary: Django logging of daily active users
Home-page: https://github.com/muckrock/daily-active-users/
Author: Mitchell Kotler
Author-email: mitch@muckrock.com
License: UNKNOWN
Platform: UNKNOWN
Classifier: Programming Language :: Python :: 3
Classifier: License :: OSI Approved :: BSD License
Classifier: Operating System :: OS Independent
Requires-Python: >=3.6
License-File: LICENSE
Requires-Dist: django
